LICENSE
MANIFEST.in
README.md
README.rst
aggregate6.7
requirements.txt
setup.py
aggregate6/__init__.py
aggregate6/__main__.py
aggregate6/aggregate6.py
aggregate6.egg-info/PKG-INFO
aggregate6.egg-info/SOURCES.txt
aggregate6.egg-info/dependency_links.txt
aggregate6.egg-info/entry_points.txt
aggregate6.egg-info/requires.txt
aggregate6.egg-info/top_level.txt
tests/test_regression.py