Metadata-Version: 2.1
Name: aggregate6
Version: 1.0.14
Summary: IPv4 and IPv6 prefix list compressor
Home-page: https://github.com/job/aggregate6
Maintainer: Job Snijders
Maintainer-email: job@instituut.net
License: BSD 2-Clause
Keywords: ipv4 and ipv6 prefix routing networking
Classifier: Intended Audience :: Developers
Classifier: Topic :: Software Development :: Libraries :: Python Modules
Classifier: Topic :: System :: Networking
Classifier: License :: OSI Approved :: BSD License
Classifier: Programming Language :: Python :: 2.7
Classifier: Programming Language :: Python :: 3
Classifier: Programming Language :: Python :: 3.6
Classifier: Programming Language :: Python :: 3.7
Classifier: Programming Language :: Python :: 3.8
Classifier: Programming Language :: Python :: 3.9
Classifier: Programming Language :: Python :: 3.10
Classifier: Programming Language :: Python :: 3.11
Classifier: Programming Language :: Python :: 3.12
License-File: LICENSE
